{
  "operationConfig" : {
    "name" : "dbxdb_vehiclemodels_get4101",
    "type" : "MappedToBackend",
    "cachable" : false,
    "smsEnabled" : false,
    "security" : "authorized_app_user",
    "responseEncoding" : "UTF-8",
    "httpMethod" : "GET",
    "decodeResponseBody" : false,
    "odata" : [ {
      "id" : "$select",
      "dataType" : "string",
      "encode" : true,
      "accessType" : "readonly"
    }, {
      "id" : "$filter",
      "dataType" : "string",
      "encode" : true,
      "accessType" : "readonly"
    }, {
      "id" : "$orderby",
      "dataType" : "string",
      "encode" : true,
      "accessType" : "readonly"
    }, {
      "id" : "$top",
      "dataType" : "string",
      "encode" : true,
      "accessType" : "readonly"
    }, {
      "id" : "$skip",
      "dataType" : "string",
      "encode" : true,
      "accessType" : "readonly"
    }, {
      "id" : "$expand",
      "dataType" : "string",
      "encode" : true,
      "accessType" : "readonly"
    }, {
      "id" : "$batchsize",
      "dataType" : "string",
      "encode" : true,
      "accessType" : "readonly"
    }, {
      "id" : "$batchid",
      "dataType" : "string",
      "encode" : true,
      "accessType" : "readonly"
    } ],
    "oMapping" : "<?xml version=\"1.0\" encoding=\"UTF-8\" standalone=\"yes\"?><mapper xmlns=\"http://www.kony.com/ns/mapper\"><map inputpath=\"response_in\" outputpath=\"response_out\"><map inputpath=\"vehiclemodels\" outputpath=\"VehicleModels\"><set-param inputpath=\"VehicleTypeId\" outputpath=\"VehicleTypeId\"/><set-param inputpath=\"VehicleTypeName\" outputpath=\"VehicleTypeName\"/><set-param inputpath=\"ParentVehicleTypeName\" outputpath=\"ParentVehicleTypeName\"/><set-param inputpath=\"Year\" outputpath=\"Year\"/><set-param inputpath=\"Model_ID\" outputpath=\"Model_ID\"/><set-param inputpath=\"Make_ID\" outputpath=\"Make_ID\"/><set-param inputpath=\"Make_Name\" outputpath=\"Make_Name\"/><set-param inputpath=\"Model_Name\" outputpath=\"Model_Name\"/><set-param inputpath=\"id\" outputpath=\"id\"/></map></map></mapper>",
    "applyCommonMapping" : true,
    "applyRequestCommonMapping" : true,
    "applyResponseCommonMapping" : true,
    "backendMeta" : {
      "serviceName" : "ConsumerLendingDB",
      "serviceVersion" : "1.0",
      "operationName" : "dbxdb_vehiclemodels_get"
    },
    "relationshipHierarchyMapping" : {
      "children" : [ ],
      "name" : "VehicleModels",
      "actions" : {
        "get" : true
      },
      "selected" : true
    },
    "requestXmlMappingOverride" : false,
    "responseXmlMappingOverride" : false
  }
}