[ {
  "entityTypeId" : "1f934b4f-bc28-474c-9b87-87810c50961a",
  "id" : "2c8c6481-aebb-44c6-b4e6-c868f3852728",
  "name" : "Email",
  "sourceFieldname" : "Email",
  "description" : "Email",
  "dataType" : "string",
  "hasIndex" : false,
  "unique" : false,
  "primarykey" : false,
  "namefield" : false,
  "nullable" : true,
  "custom" : false,
  "createable" : true,
  "updateable" : true,
  "audit" : false,
  "customizable" : false,
  "fieldOrder" : 0,
  "fieldProperties" : {
    "autoGenerated" : "false"
  }
}, {
  "entityTypeId" : "1f934b4f-bc28-474c-9b87-87810c50961a",
  "id" : "72064e45-9907-4962-84a7-ee581105ff95",
  "name" : "FirstName",
  "sourceFieldname" : "FirstName",
  "description" : "FirstName",
  "dataType" : "string",
  "hasIndex" : false,
  "unique" : false,
  "primarykey" : false,
  "namefield" : false,
  "nullable" : true,
  "custom" : false,
  "createable" : true,
  "updateable" : true,
  "audit" : false,
  "customizable" : false,
  "fieldOrder" : 0,
  "fieldProperties" : {
    "autoGenerated" : "false"
  }
}, {
  "entityTypeId" : "1f934b4f-bc28-474c-9b87-87810c50961a",
  "id" : "79c720ba-ff34-4fb1-9645-c2c322a3aaa7",
  "name" : "LastModifiedTimeStamp",
  "sourceFieldname" : "LastModifiedTimeStamp",
  "description" : "LastModifiedTimeStamp",
  "dataType" : "date",
  "hasIndex" : false,
  "unique" : false,
  "primarykey" : false,
  "namefield" : false,
  "nullable" : true,
  "custom" : false,
  "createable" : true,
  "updateable" : true,
  "audit" : false,
  "customizable" : false,
  "fieldOrder" : 0,
  "fieldProperties" : {
    "autoGenerated" : "false"
  }
}, {
  "entityTypeId" : "1f934b4f-bc28-474c-9b87-87810c50961a",
  "id" : "199ca806-e05b-4e66-ae32-ca191bb66a1a",
  "name" : "LastName",
  "sourceFieldname" : "LastName",
  "description" : "LastName",
  "dataType" : "string",
  "hasIndex" : false,
  "unique" : false,
  "primarykey" : false,
  "namefield" : false,
  "nullable" : true,
  "custom" : false,
  "createable" : true,
  "updateable" : true,
  "audit" : false,
  "customizable" : false,
  "fieldOrder" : 0,
  "fieldProperties" : {
    "autoGenerated" : "false"
  }
}, {
  "entityTypeId" : "1f934b4f-bc28-474c-9b87-87810c50961a",
  "id" : "830c10a5-70bc-48cc-af53-b01fb9f63368",
  "name" : "MiddleName",
  "sourceFieldname" : "MiddleName",
  "description" : "MiddleName",
  "dataType" : "string",
  "hasIndex" : false,
  "unique" : false,
  "primarykey" : false,
  "namefield" : false,
  "nullable" : true,
  "custom" : false,
  "createable" : true,
  "updateable" : true,
  "audit" : false,
  "customizable" : false,
  "fieldOrder" : 0,
  "fieldProperties" : {
    "autoGenerated" : "false"
  }
}, {
  "entityTypeId" : "1f934b4f-bc28-474c-9b87-87810c50961a",
  "id" : "36e41f07-c31c-498c-a827-35935f37b84b",
  "name" : "Status_id",
  "sourceFieldname" : "Status_id",
  "description" : "Status_id",
  "dataType" : "string",
  "hasIndex" : false,
  "unique" : false,
  "primarykey" : false,
  "namefield" : false,
  "nullable" : true,
  "custom" : false,
  "createable" : true,
  "updateable" : true,
  "audit" : false,
  "customizable" : false,
  "fieldOrder" : 0,
  "fieldProperties" : {
    "autoGenerated" : "false"
  }
}, {
  "entityTypeId" : "1f934b4f-bc28-474c-9b87-87810c50961a",
  "id" : "84256cc3-e4a9-4f66-9a79-8a26176c3638",
  "name" : "UpdatedBy",
  "sourceFieldname" : "UpdatedBy",
  "description" : "UpdatedBy",
  "dataType" : "string",
  "hasIndex" : false,
  "unique" : false,
  "primarykey" : false,
  "namefield" : false,
  "nullable" : true,
  "custom" : false,
  "createable" : true,
  "updateable" : true,
  "audit" : false,
  "customizable" : false,
  "fieldOrder" : 0,
  "fieldProperties" : {
    "autoGenerated" : "false"
  }
}, {
  "entityTypeId" : "1f934b4f-bc28-474c-9b87-87810c50961a",
  "id" : "b7e6c545-74ae-40fe-bc43-247f9d8c7537",
  "name" : "UserID",
  "sourceFieldname" : "UserID",
  "description" : "UserID",
  "dataType" : "string",
  "hasIndex" : false,
  "unique" : false,
  "primarykey" : false,
  "namefield" : false,
  "nullable" : true,
  "custom" : false,
  "createable" : true,
  "updateable" : true,
  "audit" : false,
  "customizable" : false,
  "fieldOrder" : 0,
  "fieldProperties" : {
    "autoGenerated" : "false"
  }
}, {
  "entityTypeId" : "1f934b4f-bc28-474c-9b87-87810c50961a",
  "id" : "dce39492-1664-4336-b68a-7b4690db6894",
  "name" : "Username",
  "sourceFieldname" : "Username",
  "description" : "Username",
  "dataType" : "string",
  "hasIndex" : false,
  "unique" : false,
  "primarykey" : false,
  "namefield" : false,
  "nullable" : true,
  "custom" : false,
  "createable" : true,
  "updateable" : true,
  "audit" : false,
  "customizable" : false,
  "fieldOrder" : 0,
  "fieldProperties" : {
    "autoGenerated" : "false"
  }
} ]