<?xml version="1.0" encoding="UTF-8" standalone="yes"?>
<service serviceGroup="" cachable="false" cacheduration="" description="" endpoint="default" groupType="" id="getRequestMessages" passwordencrypted="false" security="authorized_app_user" type="javaConnector" smscode="" smsenabled="false">
    <service-config>
        <config-param api-version="" appid="" name="preprocessorname" value=""/>
        <config-param api-version="" appid="" name="postprocessorname" value=""/>
        <config-param api-version="" appid="" name="preprocessorJS" value=""/>
        <config-param api-version="" appid="" name="postprocessorJS" value=""/>
        <config-param api-version="" appid="" name="kony_http_supported_methods" value="POST"/>
        <config-param api-version="" appid="" name="className" value="com.kony.adminconsole.service.customerrequest.CustomerRequestMessageGetService"/>
        <config-param api-version="" appid="" name="methodName" value="getRequestMessages"/>
        <config-param api-version="" appid="" name="sockettimeout" value=""/>
    </service-config>
    <service-input passthrough="false">
        <param datatype="string" defaultvalue="" description="" encode="false" format="None" formatvalue="" name="customerID" order="" paramOrder="0" parentOrder="0" passnull="false" sms-name="" src="request" sourcevalue="" srcformatvalue="" target="request" targetdatatype="java.lang.String" testvalue="" value="">
            <accessType></accessType>
        </param>
        <param datatype="string" defaultvalue="" description="" encode="false" format="None" formatvalue="" name="customerName" order="" paramOrder="0" parentOrder="0" passnull="false" sms-name="" src="request" sourcevalue="" srcformatvalue="" target="request" targetdatatype="java.lang.String" testvalue="" value="">
            <accessType></accessType>
        </param>
        <param datatype="string" defaultvalue="" description="" encode="false" format="None" formatvalue="" name="customerFirstName" order="" paramOrder="0" parentOrder="0" passnull="false" sms-name="" src="request" sourcevalue="" srcformatvalue="" target="request" targetdatatype="java.lang.String" testvalue="" value="">
            <accessType></accessType>
        </param>
        <param datatype="string" defaultvalue="" description="" encode="false" format="None" formatvalue="" name="customerMiddleName" order="" paramOrder="0" parentOrder="0" passnull="false" sms-name="" src="request" sourcevalue="" srcformatvalue="" target="request" targetdatatype="java.lang.String" testvalue="" value="">
            <accessType></accessType>
        </param>
        <param datatype="string" defaultvalue="" description="" encode="false" format="None" formatvalue="" name="customerLastName" order="" paramOrder="0" parentOrder="0" passnull="false" sms-name="" src="request" sourcevalue="" srcformatvalue="" target="request" targetdatatype="java.lang.String" testvalue="" value="">
            <accessType></accessType>
        </param>
        <param datatype="string" defaultvalue="" description="" encode="false" format="None" formatvalue="" name="requestID" order="" paramOrder="0" parentOrder="0" passnull="false" sms-name="" src="request" sourcevalue="" srcformatvalue="" target="request" targetdatatype="java.lang.String" testvalue="" value="">
            <accessType></accessType>
        </param>
        <param datatype="string" defaultvalue="" description="" encode="false" format="None" formatvalue="" name="requestSubject" order="" paramOrder="0" parentOrder="0" passnull="false" sms-name="" src="request" sourcevalue="" srcformatvalue="" target="request" targetdatatype="java.lang.String" testvalue="" value="">
            <accessType></accessType>
        </param>
        <param datatype="string" defaultvalue="" description="" encode="false" format="None" formatvalue="" name="requestStatusID" order="" paramOrder="0" parentOrder="0" passnull="false" sms-name="" src="request" sourcevalue="" srcformatvalue="" target="request" targetdatatype="java.lang.String" testvalue="" value="">
            <accessType></accessType>
        </param>
        <param datatype="string" defaultvalue="" description="" encode="false" format="None" formatvalue="" name="requestAssignedTo" order="" paramOrder="0" parentOrder="0" passnull="false" sms-name="" src="request" sourcevalue="" srcformatvalue="" target="request" targetdatatype="java.lang.String" testvalue="" value="">
            <accessType></accessType>
        </param>
        <param datatype="string" defaultvalue="" description="" encode="false" format="None" formatvalue="" name="requestCategory" order="" paramOrder="0" parentOrder="0" passnull="false" sms-name="" src="request" sourcevalue="" srcformatvalue="" target="request" targetdatatype="java.lang.String" testvalue="" value="">
            <accessType></accessType>
        </param>
        <param datatype="string" defaultvalue="" description="" encode="false" format="None" formatvalue="" name="messageRepliedBy" order="" paramOrder="0" parentOrder="0" passnull="false" sms-name="" src="request" sourcevalue="" srcformatvalue="" target="request" targetdatatype="java.lang.String" testvalue="" value="">
            <accessType></accessType>
        </param>
        <param datatype="string" defaultvalue="" description="" encode="false" format="None" formatvalue="" name="dateInitialPoint" order="" paramOrder="0" parentOrder="0" passnull="false" sms-name="" src="request" sourcevalue="" srcformatvalue="" target="request" targetdatatype="java.lang.String" testvalue="" value="">
            <accessType></accessType>
        </param>
        <param datatype="string" defaultvalue="" description="" encode="false" format="None" formatvalue="" name="dateFinalPoint" order="" paramOrder="0" parentOrder="0" passnull="false" sms-name="" src="request" sourcevalue="" srcformatvalue="" target="request" targetdatatype="java.lang.String" testvalue="" value="">
            <accessType></accessType>
        </param>
    </service-input>
    <service-output passthrough="false"/>
</service>
